slimz/__init__.py
slimz/book.py
slimz/color.py
slimz-0.0.8.dist-info/LICENSE
slimz-0.0.8.dist-info/METADATA
slimz-0.0.8.dist-info/WHEEL
slimz-0.0.8.dist-info/top_level.txt
slimz-0.0.8.dist-info/RECORD
