Metadata-Version: 2.1
Name: slimz
Version: 0.0.8
Summary: utils for python
Home-page: https://github.com/scott-x/pyutils
Author: scott
Author-email: mbp98k@gmail.com
License: UNKNOWN
Platform: UNKNOWN
Classifier: Programming Language :: Python :: 3
Classifier: License :: OSI Approved :: MIT License
Classifier: Operating System :: OS Independent
Requires-Dist: xlrd
Requires-Dist: xlwt
Requires-Dist: xlutils
Requires-Dist: colorama
